tcintegral/__init__.py
tcintegral/basis_set.py
tcintegral/contracted.py
tcintegral/grid.py
tcintegral/integrals.py
tcintegral/molecular_orbital.py
tcintegral/overlap_matrix.py
tcintegral/primitive.py
tcintegral/reactant.py
tcintegral/basis_sets/cc-pvdz.1.cp2k
tcintegral/basis_sets/sto-2g.1.cp2k
tcintegral/basis_sets/sto-3g.1.cp2k
tcintegral/basis_sets/sto-6g.1.cp2k
TCintegral-1.0.2.dist-info/LICENSE
TCintegral-1.0.2.dist-info/METADATA
TCintegral-1.0.2.dist-info/WHEEL
TCintegral-1.0.2.dist-info/top_level.txt
TCintegral-1.0.2.dist-info/RECORD
