Metadata-Version: 2.1
Name: TCintegral
Version: 1.0.2
Summary: Fast molecular integrals in Python
Author-email: Yuman Hordijk <yumanhordijk@gmail.com>
Classifier: Programming Language :: Python :: 3
Classifier: License :: OSI Approved :: MIT License
Classifier: Operating System :: OS Independent
Requires-Python: >=3.7
License-File: LICENSE
